Metadata-Version: 2.1
Name: brie
Version: 2.3.0
Summary: BRIE: Bayesian regression for isoform estimate
Home-page: https://brie.readthedocs.io
Author: Yuanhua Huang
Author-email: yuanhua@hku.hk
License: Apache-2.0
Keywords: RNA splicing,Bayesian regression,single cell RNA-seq,variantional inference
Requires-Python: >=3.5
License-File: LICENSE
Requires-Dist: anndata>=0.6
Requires-Dist: scanpy>=1.5
Requires-Dist: pysam>=0.15.2
Requires-Dist: numpy>=1.18.0
Requires-Dist: scipy>=1.4.1
Requires-Dist: statsmodels>=0.11
Requires-Dist: pandas>=0.23.0
Requires-Dist: h5py>=2.9.0
Requires-Dist: matplotlib>=3.1.2
Requires-Dist: seaborn>=0.10.0
Requires-Dist: tensorflow>=2.0.0
Requires-Dist: tensorflow-probability>=0.8.0
Requires-Dist: scikit-learn>=0.23
Requires-Dist: click>=7.0.0
Provides-Extra: docs
Requires-Dist: sphinx_bootstrap_theme; extra == "docs"
